synthdata/__init__.py
synthdata/_datahub.py
synthdata/_transformer.py
synthdata/encoder/__init__.py
synthdata/encoder/_classes.py
synthdata/encoder/_functions.py
synthdata/generator/_GMM.py
synthdata/generator/_KDE.py
synthdata/generator/_VAE.py
synthdata/generator/__init__.py
synthdata/generator/_auto.py
synthdata/generator/_base.py
synthdata/validator/_EMD.py
synthdata/validator/__init__.py
synthdata-0.0.3.dist-info/LICENSE
synthdata-0.0.3.dist-info/METADATA
synthdata-0.0.3.dist-info/WHEEL
synthdata-0.0.3.dist-info/top_level.txt
synthdata-0.0.3.dist-info/RECORD
